lfsutils/__init__.py
lfsutils/cli.py
lfsutils/lib.py
lfsutils-1.0.2.dist-info/METADATA
lfsutils-1.0.2.dist-info/WHEEL
lfsutils-1.0.2.dist-info/entry_points.txt
lfsutils-1.0.2.dist-info/licenses/LICENSE
lfsutils-1.0.2.dist-info/RECORD
